[
  {
    "reviewId": "REV001",
    "productId": "SP01",
    "userId": "user_001",
    "userName": "Minh Anh",
    "orderId": "ORD001",
    "title": "Làm sạch rất hiệu quả",
    "rating": 5,
    "comment": "Sữa rửa mặt này làm sạch sâu mà vẫn không gây khô da. Da mình ít bóng nhờn hơn sau 2 tuần dùng.",
    "images": ["assets/images/sp01-review-1.jpg"],
    "createdAt": "2024-07-15T08:30:00.000Z"
  },
  {
    "reviewId": "REV002",
    "productId": "SP01",
    "userId": "user_002",
    "userName": "Thu Hà",
    "orderId": "ORD002",
    "title": "Da sáng hơn rõ rệt",
    "rating": 4,
    "comment": "Mình dùng cho da dầu và thấy lỗ chân lông bớt to hơn. Chỉ có điều hơi khô nhẹ sau khi rửa.",
    "images": [],
    "createdAt": "2024-07-12T09:15:00.000Z"
  },
  {
    "reviewId": "REV003",
    "productId": "SP01",
    "userId": "user_003",
    "userName": "Quang Huy",
    "orderId": "ORD003",
    "title": "Phù hợp cho da mụn",
    "rating": 5,
    "comment": "Mình rất thích thành phần BHA, mụn đầu đen giảm khá nhiều. Sản phẩm xứng đáng với giá tiền.",
    "images": ["assets/images/sp01-review-2.jpg"],
    "createdAt": "2024-06-30T10:00:00.000Z"
  },
  {
    "reviewId": "REV004",
    "productId": "SP02",
    "userId": "user_004",
    "userName": "Linh Chi",
    "orderId": "ORD004",
    "title": "Dịu nhẹ và cấp ẩm tốt",
    "rating": 5,
    "comment": "Sữa rửa mặt này rất dịu, phù hợp cho da nhạy cảm. Sau một tháng da mềm và không căng hơn.",
    "images": [],
    "createdAt": "2024-07-18T12:00:00.000Z"
  },
  {
    "reviewId": "REV005",
    "productId": "SP02",
    "userId": "user_005",
    "userName": "Đức Nam",
    "orderId": "ORD005",
    "title": "Rất thích cảm giác sau khi rửa",
    "rating": 4,
    "comment": "Sản phẩm không gây khô, bọt vừa đủ. Da mình cảm thấy sạch nhưng vẫn ấm áp.",
    "images": [],
    "createdAt": "2024-07-10T14:25:00.000Z"
  },
  {
    "reviewId": "REV006",
    "productId": "SP02",
    "userId": "user_006",
    "userName": "Hà My",
    "orderId": "ORD006",
    "title": "Phù hợp cho da khô",
    "rating": 5,
    "comment": "Đây là loại sữa rửa mặt đầu tiên của mình không làm da bị căng sau khi dùng. Cực kỳ đáng mua.",
    "images": ["assets/images/sp02-review-1.jpg"],
    "createdAt": "2024-06-28T07:40:00.000Z"
  },
  {
    "reviewId": "REV007",
    "productId": "SP03",
    "userId": "user_007",
    "userName": "Bảo Trâm",
    "orderId": "ORD007",
    "title": "Da sáng lên rõ rệt",
    "rating": 4,
    "comment": "Da mình xỉn màu hơn trước sau vài tuần dùng. Mùi thơm nhẹ và rất dễ dùng.",
    "images": [],
    "createdAt": "2024-07-08T09:50:00.000Z"
  },
  {
    "reviewId": "REV008",
    "productId": "SP03",
    "userId": "user_008",
    "userName": "Phúc An",
    "orderId": "ORD008",
    "title": "Một sản phẩm đáng dùng",
    "rating": 5,
    "comment": "Mình thấy làn da khỏe hơn và tươi sáng hơn. Sẽ tiếp tục dùng lâu dài.",
    "images": ["assets/images/sp03-review-1.jpg"],
    "createdAt": "2024-06-20T16:10:00.000Z"
  },
  {
    "reviewId": "REV009",
    "productId": "SP03",
    "userId": "user_009",
    "userName": "Khoa",
    "orderId": "ORD009",
    "title": "Cảm giác sạch nhưng không quá khô",
    "rating": 4,
    "comment": "Mình dùng cho da hỗn hợp và thấy khá ổn. Sản phẩm không gây kích ứng.",
    "images": [],
    "createdAt": "2024-06-05T11:20:00.000Z"
  },
  {
    "reviewId": "REV010",
    "productId": "SP04",
    "userId": "user_010",
    "userName": "Lan Nhi",
    "orderId": "ORD010",
    "title": "Cho da lão hóa khá ổn",
    "rating": 5,
    "comment": "Mình thấy da mềm và săn chắc hơn sau thời gian dùng. Sẽ mua tiếp.",
    "images": [],
    "createdAt": "2024-07-21T08:40:00.000Z"
  },
  {
    "reviewId": "REV011",
    "productId": "SP04",
    "userId": "user_011",
    "userName": "Tùng",
    "orderId": "ORD011",
    "title": "Dùng được lâu dài",
    "rating": 4,
    "comment": "Sản phẩm không gây bết dính, kết cấu khá mịn. Da mình cảm thấy thư giãn hơn.",
    "images": [],
    "createdAt": "2024-07-03T15:35:00.000Z"
  },
  {
    "reviewId": "REV012",
    "productId": "SP04",
    "userId": "user_012",
    "userName": "Yến Vy",
    "orderId": "ORD012",
    "title": "Đáng đầu tư",
    "rating": 5,
    "comment": "Mình dùng trong vài tuần và thấy nếp nhăn khuôn mặt ít rõ hơn. Rất hài lòng.",
    "images": ["assets/images/sp04-review-1.jpg"],
    "createdAt": "2024-06-25T19:05:00.000Z"
  },
  {
    "reviewId": "REV013",
    "productId": "SP05",
    "userId": "user_013",
    "userName": "Nhã",
    "orderId": "ORD013",
    "title": "Lỗ chân lông giảm rõ",
    "rating": 5,
    "comment": "Sau 3 tuần dùng, da ít dầu và lỗ chân lông nhìn nhỏ hơn rất nhiều.",
    "images": [],
    "createdAt": "2024-07-14T10:20:00.000Z"
  },
  {
    "reviewId": "REV014",
    "productId": "SP05",
    "userId": "user_014",
    "userName": "Hồng Phúc",
    "orderId": "ORD014",
    "title": "Dễ dùng và hiệu quả",
    "rating": 4,
    "comment": "Dùng rất mịn, không gây cay. Mình thấy mặt ít đổ dầu hơn vào buổi chiều.",
    "images": [],
    "createdAt": "2024-07-02T17:10:00.000Z"
  },
  {
    "reviewId": "REV015",
    "productId": "SP05",
    "userId": "user_015",
    "userName": "Kim Oanh",
    "orderId": "ORD015",
    "title": "Thích nhất là cảm giác sạch sâu",
    "rating": 5,
    "comment": "Mình dùng 2 lần/ngày và thấy da thông thoáng hơn. Sản phẩm rất đáng tiền.",
    "images": ["assets/images/sp05-review-1.jpg"],
    "createdAt": "2024-06-18T13:50:00.000Z"
  },
  {
    "reviewId": "REV016",
    "productId": "SP06",
    "userId": "user_016",
    "userName": "Hải Yến",
    "orderId": "ORD016",
    "title": "Mùi thơm dịu và dễ dùng",
    "rating": 4,
    "comment": "Sản phẩm rất tiện lợi, dùng lâu dài không bị bết. Da mình cảm thấy mềm hơn mỗi ngày.",
    "images": [],
    "createdAt": "2024-07-22T09:00:00.000Z"
  },
  {
    "reviewId": "REV017",
    "productId": "SP06",
    "userId": "user_017",
    "userName": "Bình An",
    "orderId": "ORD017",
    "title": "Đánh giá rất ổn",
    "rating": 5,
    "comment": "Mình thấy hiệu quả rõ sau vài tuần. Sẽ giới thiệu cho bạn bè.",
    "images": [],
    "createdAt": "2024-06-24T11:40:00.000Z"
  },
  {
    "reviewId": "REV018",
    "productId": "SP07",
    "userId": "user_018",
    "userName": "Vân Anh",
    "orderId": "ORD018",
    "title": "Cực kỳ đáng mua",
    "rating": 5,
    "comment": "Mình thích cách sản phẩm chăm sóc da mà không gây kích ứng. Kết cấu mịn và thơm nhẹ.",
    "images": [],
    "createdAt": "2024-07-19T08:20:00.000Z"
  },
  {
    "reviewId": "REV019",
    "productId": "SP07",
    "userId": "user_019",
    "userName": "Khánh Linh",
    "orderId": "ORD019",
    "title": "Phù hợp cho da nhạy cảm",
    "rating": 4,
    "comment": "Da mình không hề bị đỏ sau khi dùng. Rất ưng ý với cảm giác mềm mại.",
    "images": [],
    "createdAt": "2024-06-29T16:00:00.000Z"
  },
  {
    "reviewId": "REV020",
    "productId": "SP08",
    "userId": "user_020",
    "userName": "Ngọc Linh",
    "orderId": "ORD020",
    "title": "Dùng khá ổn",
    "rating": 4,
    "comment": "Sản phẩm dễ thoa, thấm nhanh và không bết. Mình thấy da đều màu hơn.",
    "images": [],
    "createdAt": "2024-07-16T10:15:00.000Z"
  },
  {
    "reviewId": "REV021",
    "productId": "SP08",
    "userId": "user_021",
    "userName": "Tuấn Anh",
    "orderId": "ORD021",
    "title": "Rất thích bảng thành phần",
    "rating": 5,
    "comment": "Thành phần rõ ràng, dùng lâu dài khá an tâm. Da mình cũng cải thiện rõ.",
    "images": [],
    "createdAt": "2024-06-21T14:35:00.000Z"
  },
  {
    "reviewId": "REV022",
    "productId": "SP09",
    "userId": "user_022",
    "userName": "Mai Trang",
    "orderId": "ORD022",
    "title": "Tươi sáng hơn sau vài tuần",
    "rating": 5,
    "comment": "Mình thấy da sáng và đều màu hơn. Sản phẩm dùng rất mịn và dễ chịu.",
    "images": [],
    "createdAt": "2024-07-11T12:05:00.000Z"
  },
  {
    "reviewId": "REV023",
    "productId": "SP09",
    "userId": "user_023",
    "userName": "Hoàng Nam",
    "orderId": "ORD023",
    "title": "Hiệu quả tốt cho da dầu",
    "rating": 4,
    "comment": "Không gây bí da, lại làm da sạch sảng hơn. Mình khá hài lòng.",
    "images": [],
    "createdAt": "2024-06-27T09:55:00.000Z"
  },
  {
    "reviewId": "REV024",
    "productId": "SP10",
    "userId": "user_024",
    "userName": "Phương Uyên",
    "orderId": "ORD024",
    "title": "Da mềm hơn rõ rệt",
    "rating": 5,
    "comment": "Sau khoảng 2 tuần dùng, mặt mình mềm và không bị căng. Sản phẩm rất hợp.",
    "images": [],
    "createdAt": "2024-07-24T13:30:00.000Z"
  },
  {
    "reviewId": "REV025",
    "productId": "SP10",
    "userId": "user_025",
    "userName": "Đông Hà",
    "orderId": "ORD025",
    "title": "Không gây kích ứng",
    "rating": 4,
    "comment": "Mình dùng cho da nhạy cảm và thấy khá ổn. Sản phẩm rất dịu.",
    "images": [],
    "createdAt": "2024-06-17T07:45:00.000Z"
  },
  {
    "reviewId": "REV026",
    "productId": "SP11",
    "userId": "user_026",
    "userName": "Huyền Trân",
    "orderId": "ORD026",
    "title": "Dễ dùng và hiệu quả",
    "rating": 4,
    "comment": "Tạo cảm giác sạch sâu nhưng vẫn mềm da. Mình dùng thả ga mỗi tối.",
    "images": [],
    "createdAt": "2024-07-06T15:40:00.000Z"
  },
  {
    "reviewId": "REV027",
    "productId": "SP11",
    "userId": "user_027",
    "userName": "Long",
    "orderId": "ORD027",
    "title": "Rất đáng tiền",
    "rating": 5,
    "comment": "Sản phẩm cho hiệu quả tốt hơn mong đợi. Mình sẽ tiếp tục dùng.",
    "images": [],
    "createdAt": "2024-06-12T10:20:00.000Z"
  },
  {
    "reviewId": "REV028",
    "productId": "SP12",
    "userId": "user_028",
    "userName": "Nhật Vy",
    "orderId": "ORD028",
    "title": "Mịn màng và thư giãn",
    "rating": 5,
    "comment": "Sản phẩm có texture mịn, dùng rất thích. Da mềm hơn sau vài ngày.",
    "images": [],
    "createdAt": "2024-07-09T11:10:00.000Z"
  },
  {
    "reviewId": "REV029",
    "productId": "SP12",
    "userId": "user_029",
    "userName": "Mạnh Dũng",
    "orderId": "ORD029",
    "title": "Dùng ổn định",
    "rating": 4,
    "comment": "Không gây bết dính, dùng rất tiện. Mình thấy da sáng hơn chút ít.",
    "images": [],
    "createdAt": "2024-06-22T17:30:00.000Z"
  },
  {
    "reviewId": "REV030",
    "productId": "SP13",
    "userId": "user_030",
    "userName": "Linh Đan",
    "orderId": "ORD030",
    "title": "Sạch sâu mà vẫn dịu",
    "rating": 5,
    "comment": "Mình thích cảm giác da lau sạch mà vẫn mềm. Thành phần cũng khá thoải mái.",
    "images": [],
    "createdAt": "2024-07-07T08:45:00.000Z"
  },
  {
    "reviewId": "REV031",
    "productId": "SP13",
    "userId": "user_031",
    "userName": "Trung Hiếu",
    "orderId": "ORD031",
    "title": "Đáng dùng",
    "images": [],
    "rating": 4,
    "comment": "Dùng trong thời gian ngắn thấy da khá ổn. Ít bị bóng dầu hơn.",
    "createdAt": "2024-06-23T12:55:00.000Z"
  },
  {
    "reviewId": "REV032",
    "productId": "SP14",
    "userId": "user_032",
    "userName": "Ánh Dương",
    "orderId": "ORD032",
    "title": "Tốt cho da dầu",
    "rating": 4,
    "comment": "Mặt mình ít bóng dầu hơn sau vài tuần. Sản phẩm không quá nặng.",
    "images": [],
    "createdAt": "2024-07-05T14:15:00.000Z"
  },
  {
    "reviewId": "REV033",
    "productId": "SP14",
    "userId": "user_033",
    "userName": "Kỳ Duyên",
    "orderId": "ORD033",
    "title": "Cảm giác rất mượt",
    "rating": 5,
    "comment": "Da mình mềm hơn và finish rất mịn. Sẽ dùng tiếp.",
    "images": [],
    "createdAt": "2024-06-26T09:12:00.000Z"
  },
  {
    "reviewId": "REV034",
    "productId": "SP15",
    "userId": "user_034",
    "userName": "Thảo My",
    "orderId": "ORD034",
    "title": "Da sáng hơn",
    "rating": 4,
    "comment": "Mình thấy da thông thoáng và đều màu hơn sau một thời gian dùng.",
    "images": [],
    "createdAt": "2024-07-04T07:25:00.000Z"
  },
  {
    "reviewId": "REV035",
    "productId": "SP15",
    "userId": "user_035",
    "userName": "Quốc Huy",
    "orderId": "ORD035",
    "title": "Rất thích texture",
    "rating": 5,
    "comment": "Texture vừa phải, không quá lỏng. Mình dùng khá thích.",
    "images": [],
    "createdAt": "2024-06-19T16:40:00.000Z"
  },
  {
    "reviewId": "REV036",
    "productId": "SP16",
    "userId": "user_036",
    "userName": "Minh Khuê",
    "orderId": "ORD036",
    "title": "Đẹp da hơn",
    "rating": 5,
    "comment": "Sản phẩm có vẻ dưỡng ẩm rất tốt. Da mình mịn màng hơn sau một tháng.",
    "images": [],
    "createdAt": "2024-07-13T10:05:00.000Z"
  },
  {
    "reviewId": "REV037",
    "productId": "SP16",
    "userId": "user_037",
    "userName": "Cường",
    "orderId": "ORD037",
    "title": "Ổn áp và dễ dùng",
    "rating": 4,
    "comment": "Không gây khó chịu, dùng khá tiện và phù hợp cho lịch trình bận rộn.",
    "images": [],
    "createdAt": "2024-06-16T13:50:00.000Z"
  },
  {
    "reviewId": "REV038",
    "productId": "SP17",
    "userId": "user_038",
    "userName": "Ngọc Trâm",
    "orderId": "ORD038",
    "title": "Thơm nhẹ và dịu",
    "rating": 4,
    "comment": "Mình khá thích hương thơm dịu và cảm giác da sạch sau khi dùng.",
    "images": [],
    "createdAt": "2024-07-17T08:20:00.000Z"
  },
  {
    "reviewId": "REV039",
    "productId": "SP17",
    "userId": "user_039",
    "userName": "Sơn Tùng",
    "orderId": "ORD039",
    "title": "Rất đáng thử",
    "rating": 5,
    "comment": "Sản phẩm khá ổn, da mình thấy mềm và đều màu hơn. Sẽ mua tiếp.",
    "images": [],
    "createdAt": "2024-06-15T11:25:00.000Z"
  },
  {
    "reviewId": "REV040",
    "productId": "SP18",
    "userId": "user_040",
    "userName": "Mỹ Hạnh",
    "orderId": "ORD040",
    "title": "Đúng như mô tả",
    "rating": 4,
    "comment": "Mình thấy sản phẩm đúng như thông tin trên website. Dùng rất dễ chịu.",
    "images": [],
    "createdAt": "2024-07-20T09:35:00.000Z"
  },
  {
    "reviewId": "REV041",
    "productId": "SP18",
    "userId": "user_041",
    "userName": "Đức Minh",
    "orderId": "ORD041",
    "title": "Chất lượng tốt",
    "rating": 5,
    "comment": "Thật sự ưng với chất lượng và cách sản phẩm chăm sóc da.",
    "images": [],
    "createdAt": "2024-06-14T15:50:00.000Z"
  },
  {
    "reviewId": "REV042",
    "productId": "SP19",
    "userId": "user_042",
    "userName": "Yến Nhi",
    "orderId": "ORD042",
    "title": "Mềm da nhanh",
    "rating": 5,
    "comment": "Da mình mềm hơn sau vài lần dùng. Không gây nặng mặt.",
    "images": [],
    "createdAt": "2024-07-23T12:20:00.000Z"
  },
  {
    "reviewId": "REV043",
    "productId": "SP19",
    "userId": "user_043",
    "userName": "Tấn Phát",
    "orderId": "ORD043",
    "title": "Rất ổn",
    "rating": 4,
    "comment": "Sản phẩm dùng thư giãn, da cũng không bị khô sau khi rửa.",
    "images": [],
    "createdAt": "2024-06-13T10:40:00.000Z"
  },
  {
    "reviewId": "REV044",
    "productId": "SP20",
    "userId": "user_044",
    "userName": "Như Quỳnh",
    "orderId": "ORD044",
    "title": "Dùng khá hợp",
    "rating": 4,
    "comment": "Mình thấy da tươi sáng hơn và không bị căng. Sản phẩm khá dễ dùng.",
    "images": [],
    "createdAt": "2024-07-25T09:00:00.000Z"
  },
  {
    "reviewId": "REV045",
    "productId": "SP20",
    "userId": "user_045",
    "userName": "Bảo Châu",
    "orderId": "ORD045",
    "title": "Cực kỳ ưng",
    "rating": 5,
    "comment": "Mình dùng vài tuần và cảm thấy lớp da trên mặt mịn hơn rõ rệt.",
    "images": [],
    "createdAt": "2024-06-11T18:20:00.000Z"
  },
  {
    "reviewId": "REV046",
    "productId": "SP21",
    "userId": "user_046",
    "userName": "Lâm Oanh",
    "orderId": "ORD046",
    "title": "Chất lượng vượt mong đợi",
    "rating": 5,
    "comment": "Sản phẩm làm sạch rất tốt, da mình không còn bị bí sau dùng.",
    "images": [],
    "createdAt": "2024-07-26T14:10:00.000Z"
  },
  {
    "reviewId": "REV047",
    "productId": "SP21",
    "userId": "user_047",
    "userName": "Vũ An",
    "orderId": "ORD047",
    "title": "Rất tiện cho nhu cầu hằng ngày",
    "rating": 4,
    "comment": "Dùng rất tiện, không khó chịu và khá dễ thích nghi với da.",
    "images": [],
    "createdAt": "2024-06-10T08:55:00.000Z"
  },
  {
    "reviewId": "REV048",
    "productId": "SP22",
    "userId": "user_048",
    "userName": "Thùy Dương",
    "orderId": "ORD048",
    "title": "Mịn và dịu",
    "rating": 5,
    "comment": "Mình thấy da sạch hơn và mềm hơn sau một thời gian dùng.",
    "images": [],
    "createdAt": "2024-07-27T11:40:00.000Z"
  },
  {
    "reviewId": "REV049",
    "productId": "SP22",
    "userId": "user_049",
    "userName": "Hưng",
    "orderId": "ORD049",
    "title": "Ổn định và dễ dùng",
    "rating": 4,
    "comment": "Sản phẩm nhẹ, dễ thoa và không gây kích ứng. Mình hài lòng.",
    "images": [],
    "createdAt": "2024-06-09T16:15:00.000Z"
  },
  {
    "reviewId": "REV050",
    "productId": "SP23",
    "userId": "U1782100000001",
    "userName": "Ngô Thanh Trúc",
    "orderId": "ORD501",
    "title": "Da sáng hơn sau vài tuần",
    "rating": 5,
    "comment": "Serum này dùng rất dịu, da mình sáng và đều màu hơn sau khoảng 2 tuần. Rất thích.",
    "images": [],
    "createdAt": "2024-07-20T08:10:00.000Z"
  },
  {
    "reviewId": "REV051",
    "productId": "SP23",
    "userId": "U1782100000002",
    "userName": "Phạm Gia Hân",
    "orderId": "ORD502",
    "title": "Dưỡng sáng rất ổn",
    "rating": 4,
    "comment": "Mình thấy da sáng hơn và không bị kích ứng. Kết cấu serum cũng dễ thoa.",
    "images": [],
    "createdAt": "2024-07-16T10:25:00.000Z"
  },
  {
    "reviewId": "REV052",
    "productId": "SP24",
    "userId": "U1782100000003",
    "userName": "Nguyễn Minh Khánh",
    "orderId": "ORD505",
    "title": "Kem dưỡng rất mềm mại",
    "rating": 5,
    "comment": "Kem có texture mịn, thấm khá nhanh và da mình thấy mềm hơn sau vài ngày dùng.",
    "images": [],
    "createdAt": "2024-07-18T09:30:00.000Z"
  },
  {
    "reviewId": "REV053",
    "productId": "SP24",
    "userId": "U1782100000004",
    "userName": "Trần Thị Hòa",
    "orderId": "ORD506",
    "title": "Dưỡng ẩm tốt",
    "rating": 4,
    "comment": "Mình dùng cho da khô và thấy ít căng hơn. Sản phẩm rất đáng mua.",
    "images": [],
    "createdAt": "2024-07-14T13:45:00.000Z"
  },
  {
    "reviewId": "REV054",
    "productId": "SP25",
    "userId": "U1782100000005",
    "userName": "Lê Quang Duy",
    "orderId": "ORD509",
    "title": "Chống nắng dễ chịu",
    "rating": 5,
    "comment": "Kem chống nắng không bị nhờn, lên da mịn và rất dễ chịu khi sử dụng hằng ngày.",
    "images": [],
    "createdAt": "2024-07-12T07:20:00.000Z"
  },
  {
    "reviewId": "REV055",
    "productId": "SP25",
    "userId": "U1782100000006",
    "userName": "Võ Bảo Trân",
    "orderId": "ORD510",
    "title": "Thấm nhanh và không bết",
    "rating": 4,
    "comment": "Mình thấy sản phẩm thấm khá nhanh, da không bị bết dính sau khi dùng.",
    "images": [],
    "createdAt": "2024-07-09T15:10:00.000Z"
  },
  {
    "reviewId": "REV056",
    "productId": "SP26",
    "userId": "U1782100000007",
    "userName": "Đặng Thảo Nhi",
    "orderId": "ORD513",
    "title": "Làm sạch dịu và thoải mái",
    "rating": 5,
    "comment": "Sữa rửa mặt này rất dịu, không gây căng da sau khi rửa. Mình thích dùng mỗi tối.",
    "images": [],
    "createdAt": "2024-07-08T11:35:00.000Z"
  },
  {
    "reviewId": "REV057",
    "productId": "SP26",
    "userId": "U1782100000008",
    "userName": "Huỳnh Minh An",
    "orderId": "ORD514",
    "title": "Phù hợp với da nhạy cảm",
    "rating": 4,
    "comment": "Da mình hơi nhạy nên khá sợ dùng sữa rửa mặt mới, nhưng sản phẩm này không gây khó chịu.",
    "images": [],
    "createdAt": "2024-07-05T16:45:00.000Z"
  },
  {
    "reviewId": "REV058",
    "productId": "SP27",
    "userId": "U1782100000001",
    "userName": "Ngô Thanh Trúc",
    "orderId": "ORD517",
    "title": "Cấp ẩm rất tốt",
    "rating": 5,
    "comment": "Toner này làm da mềm hơn and không bị khô sau khi dùng. Mình thấy da căng mọng hơn.",
    "images": [],
    "createdAt": "2024-07-21T12:00:00.000Z"
  },
  {
    "reviewId": "REV059",
    "productId": "SP27",
    "userId": "U1782100000002",
    "userName": "Phạm Gia Hân",
    "orderId": "ORD518",
    "title": "Dễ dùng và khá hiệu quả",
    "rating": 4,
    "comment": "Toner thấm nhanh, dùng rất tiện và làm da cảm thấy thư giãn hơn sau mỗi lần dùng.",
    "images": [],
    "createdAt": "2024-07-17T09:40:00.000Z"
  },
  {
    "reviewId": "REV060",
    "productId": "SP29",
    "userId": "U1782100000005",
    "userName": "Lê Quang Duy",
    "orderId": "ORD521",
    "title": "Kem ban đêm rất dưỡng",
    "rating": 5,
    "comment": "Sản phẩm dùng vào ban đêm rất thích, da mình mềm và ẩm hơn vào sáng hôm sau.",
    "images": [],
    "createdAt": "2024-07-19T20:05:00.000Z"
  },
  {
    "reviewId": "REV061",
    "productId": "SP29",
    "userId": "U1782100000006",
    "userName": "Võ Bảo Trân",
    "orderId": "ORD522",
    "title": "Phục hồi tốt",
    "rating": 4,
    "comment": "Da mình không còn cảm giác căng sau khi dùng kem này. Rất phù hợp cho da khô.",
    "images": [],
    "createdAt": "2024-07-15T22:20:00.000Z"
  },
  {
    "reviewId": "REV062",
    "productId": "SP30",
    "userId": "U1782100000001",
    "userName": "Ngô Thanh Trúc",
    "orderId": "ORD525",
    "title": "Bảo vệ tốt khi ra ngoài",
    "rating": 5,
    "comment": "Kem chống nắng này dùng rất ổn, không bị nhờn và da mình vẫn thấy thoáng khi ở ngoài nắng.",
    "images": [],
    "createdAt": "2024-07-22T08:15:00.000Z"
  },
  {
    "reviewId": "REV063",
    "productId": "SP30",
    "userId": "U1782100000002",
    "userName": "Phạm Gia Hân",
    "orderId": "ORD526",
    "title": "Dịu và bảo vệ tốt",
    "rating": 4,
    "comment": "Mình thấy sản phẩm rất dịu, phù hợp cho da nhạy cảm và bảo vệ da tốt trong ngày dài.",
    "images": [],
    "createdAt": "2024-07-13T12:30:00.000Z"
  }
]
